letter_art/converter.py
letter_art-0.2.4.dist-info/licenses/LICENSE
letter_art-0.2.4.dist-info/METADATA
letter_art-0.2.4.dist-info/WHEEL
letter_art-0.2.4.dist-info/entry_points.txt
letter_art-0.2.4.dist-info/top_level.txt
letter_art-0.2.4.dist-info/RECORD
