Metadata-Version: 2.4
Name: letter-art
Version: 0.2.4
Summary: Convert images into ASCII art in Python
Author-email: gwondoo <kdh30166568@gmail.com>
License-Expression: MIT
Project-URL: Homepage, https://github.com/gwondoo/letter_art
Requires-Python: >=3.7
License-File: LICENSE
Requires-Dist: pillow
Dynamic: license-file
